gaea/config/__init__.py
gaea/config/config.py
gaea/config/config_2.py
gaea/constants/__init__.py
gaea/database/__init__.py
gaea/database/main.py
gaea/database/utils/test.py
gaea/errors/__init__.py
gaea/helpers/__init__.py
gaea/helpers/auth.py
gaea/helpers/metaclass.py
gaea/log/__init__.py
gaea/log/main.py
gaea/models/__init__.py
gaea/models/apiaries.py
gaea/models/base.py
gaea/models/comments.py
gaea/models/events.py
gaea/models/hives.py
gaea/models/swarms.py
gaea/models/users.py
gaea/models/utils/__init__.py
gaea/models/utils/test.py
gaea/rbmq/__init__.py
gaea/rbmq/base.py
gaea/rbmq/consumer.py
gaea/rbmq/publisher.py
gaea/rbmq/utils/tests.py
gaea/redis/__init__.py
gaea/redis/client.py
gaea/redis/constants.py
gaea/redis/messages.py
gaea/webapp/__init__.py
gaea/webapp/main.py
gaea/webapp/monitoring.py
gaea/webapp/utils.py
gaea-1.9.2.dist-info/METADATA
gaea-1.9.2.dist-info/WHEEL
gaea-1.9.2.dist-info/RECORD
