Metadata-Version: 2.1
Name: gaea
Version: 1.9.2
Summary: A microservice chassis for akingbee.com !
Author: rarnal
Author-email: arnal.romain@gmail.com
Requires-Python: >=3.9
Classifier: Programming Language :: Python :: 3
Classifier: Programming Language :: Python :: 3.9
Classifier: Programming Language :: Python :: 3.10
Classifier: Programming Language :: Python :: 3.11
Requires-Dist: aiohttp (>=3.7.4,<4.0.0)
Requires-Dist: alembic (>=1,<2)
Requires-Dist: dynaconf (>=3,<4)
Requires-Dist: fastapi (>=0.65.2)
Requires-Dist: httpx (>=0.23.3,<0.24.0)
Requires-Dist: pika (>=1,<2)
Requires-Dist: psycopg2-binary (>=2,<3)
Requires-Dist: pydantic (>=1,<2)
Requires-Dist: redis (>=3,<4)
Requires-Dist: sqlalchemy (>=1)
Requires-Dist: uvicorn (>=0.11.7)
